<annotation>
  <folder>Pizza</folder>
  <filename>0467515a03e8d7d0.jpg</filename>
  <path>C:\Users\Nikhil\Desktop\New folder\OID\Dataset\train\Pizza\0467515a03e8d7d0.jpg</path>
  <source>
    <database>Unknown</database>
  </source>
  <size>
    <width>768</width>
    <height>768</height>
    <depth>3</depth>
  </size>
  <segmented>0</segmented>
  <object>
    <name>Pizza</name>
    <pose>Unspecified</pose>
    <truncated>0</truncated>
    <difficult>0</difficult>
    <bndbox>
      <xmin>146</xmin>
      <ymin>322</ymin>
      <xmax>464</xmax>
      <ymax>766</ymax>
    </bndbox>
  </object>
  <object>
    <name>Pizza</name>
    <pose>Unspecified</pose>
    <truncated>0</truncated>
    <difficult>0</difficult>
    <bndbox>
      <xmin>441</xmin>
      <ymin>287</ymin>
      <xmax>766</xmax>
      <ymax>693</ymax>
    </bndbox>
  </object>
</annotation>
