<annotation>
  <folder>Beer</folder>
  <filename>3d567939c41c2c81.jpg</filename>
  <path>C:\Users\Nikhil\Desktop\New folder\OID\Dataset\train\Beer\3d567939c41c2c81.jpg</path>
  <source>
    <database>Unknown</database>
  </source>
  <size>
    <width>1024</width>
    <height>1024</height>
    <depth>3</depth>
  </size>
  <segmented>0</segmented>
  <object>
    <name>Beer</name>
    <pose>Unspecified</pose>
    <truncated>0</truncated>
    <difficult>0</difficult>
    <bndbox>
      <xmin>18</xmin>
      <ymin>274</ymin>
      <xmax>441</xmax>
      <ymax>853</ymax>
    </bndbox>
  </object>
  <object>
    <name>Beer</name>
    <pose>Unspecified</pose>
    <truncated>0</truncated>
    <difficult>0</difficult>
    <bndbox>
      <xmin>483</xmin>
      <ymin>264</ymin>
      <xmax>1022</xmax>
      <ymax>883</ymax>
    </bndbox>
  </object>
</annotation>
