<annotation>
  <folder>Hamburger</folder>
  <filename>55a9558c4b8c22ea.jpg</filename>
  <path>C:\Users\Nikhil\Desktop\New folder\OID\Dataset\train\Hamburger\55a9558c4b8c22ea.jpg</path>
  <source>
    <database>Unknown</database>
  </source>
  <size>
    <width>1024</width>
    <height>658</height>
    <depth>3</depth>
  </size>
  <segmented>0</segmented>
  <object>
    <name>Hamburger</name>
    <pose>Unspecified</pose>
    <truncated>0</truncated>
    <difficult>0</difficult>
    <bndbox>
      <xmin>172</xmin>
      <ymin>62</ymin>
      <xmax>868</xmax>
      <ymax>568</ymax>
    </bndbox>
  </object>
</annotation>
