<annotation>
  <folder>Pizza</folder>
  <filename>7b923573b982bb27.jpg</filename>
  <path>C:\Users\Nikhil\Desktop\New folder\OID\Dataset\train\Pizza\7b923573b982bb27.jpg</path>
  <source>
    <database>Unknown</database>
  </source>
  <size>
    <width>768</width>
    <height>1024</height>
    <depth>3</depth>
  </size>
  <segmented>0</segmented>
  <object>
    <name>Pizza</name>
    <pose>Unspecified</pose>
    <truncated>0</truncated>
    <difficult>0</difficult>
    <bndbox>
      <xmin>128</xmin>
      <ymin>805</ymin>
      <xmax>359</xmax>
      <ymax>931</ymax>
    </bndbox>
  </object>
  <object>
    <name>Pizza</name>
    <pose>Unspecified</pose>
    <truncated>0</truncated>
    <difficult>0</difficult>
    <bndbox>
      <xmin>286</xmin>
      <ymin>783</ymin>
      <xmax>433</xmax>
      <ymax>915</ymax>
    </bndbox>
  </object>
  <object>
    <name>Pizza</name>
    <pose>Unspecified</pose>
    <truncated>0</truncated>
    <difficult>0</difficult>
    <bndbox>
      <xmin>407</xmin>
      <ymin>817</ymin>
      <xmax>461</xmax>
      <ymax>889</ymax>
    </bndbox>
  </object>
</annotation>
